{
  "id": "jobs-stanford",
  "videoId": "UF8uR6Z6KLc",
  "title": "史蒂夫·乔布斯斯坦福大学毕业演讲",
  "subtitle": "乔布斯分享人生三段经历：点滴相连、爱与失去、死亡，鼓励毕业生追随内心，活出自我。",
  "speakerName": "",
  "speakerAvatar": "/avatars/jobs-stanford.jpg",
  "startTime": 22,
  "duration": 909,
  "turns": [
    {
      "who": "Steve Jobs",
      "start": 0,
      "text": "Thank You. I am honored to be with you today at your commencement from one of the finest universities in the world."
    },
    {
      "who": "Steve Jobs",
      "start": 14,
      "text": "Truth be told I never graduated from college and this is the closest I've ever gotten to a college graduation."
    },
    {
      "who": "Steve Jobs",
      "start": 26,
      "text": "Today I want to tell you three stories from my life. That's it."
    },
    {
      "who": "Steve Jobs",
      "start": 30,
      "text": "No big deal. Just three stories."
    },
    {
      "who": "Steve Jobs",
      "start": 34,
      "text": "The first story is about connecting the dots."
    },
    {
      "who": "Steve Jobs",
      "start": 39,
      "text": "I dropped out of Reed College after the first 6 months, but then stayed around as a drop-in for another 18 months or so before I really quit."
    },
    {
      "who": "Steve Jobs",
      "start": 47,
      "text": "So why did I drop out?"
    },
    {
      "who": "Steve Jobs",
      "start": 50,
      "text": "It started before I was born."
    },
    {
      "who": "Steve Jobs",
      "start": 53,
      "text": "My biological mother was a young, unwed graduate student, and she decided to put me up for adoption."
    },
    {
      "who": "Steve Jobs",
      "start": 60,
      "text": "She felt very strongly that I should be adopted by college graduates, so everything was all set for me to be adopted at birth by a lawyer and his wife."
    },
    {
      "who": "Steve Jobs",
      "start": 70,
      "text": "Except that when I popped out they decided at the last minute that they really wanted a girl."
    },
    {
      "who": "Steve Jobs",
      "start": 76,
      "text": "So my parents, who were on a waiting list, got a call in the middle of the night asking: \"We have an unexpected baby boy; do you want him?\""
    },
    {
      "who": "Steve Jobs",
      "start": 85,
      "text": "They said: \"Of course.\" My biological mother later found out that my mother had never graduated from college and that my father had never graduated from high school."
    },
    {
      "who": "Steve Jobs",
      "start": 97,
      "text": "She refused to sign the final adoption papers."
    },
    {
      "who": "Steve Jobs",
      "start": 101,
      "text": "She only relented a few months later when my parents promised that I would go to college. This was the start in my life."
    },
    {
      "who": "Steve Jobs",
      "start": 111,
      "text": "And 17 years later I did go to college. But I naively chose a college that was almost as expensive as Stanford, and all of my working-class parents' savings were being spent on my college tuition."
    },
    {
      "who": "Steve Jobs",
      "start": 126,
      "text": "After six months, I couldn't see the value in it."
    },
    {
      "who": "Steve Jobs",
      "start": 129,
      "text": "I had no idea what I wanted to do with my life and no idea how college was going to help me figure it out."
    },
    {
      "who": "Steve Jobs",
      "start": 135,
      "text": "And here I was spending all of the money my parents had saved their entire life."
    },
    {
      "who": "Steve Jobs",
      "start": 141,
      "text": "So I decided to drop out and trust that it would all work out OK."
    },
    {
      "who": "Steve Jobs",
      "start": 145,
      "text": "It was pretty scary at the time, but looking back it was one of the best decisions I ever made."
    },
    {
      "who": "Steve Jobs",
      "start": 152,
      "text": "The minute I dropped out I could stop taking the required classes that didn't interest me, and begin dropping in on the ones that looked interesting."
    },
    {
      "who": "Steve Jobs",
      "start": 163,
      "text": "It wasn't all romantic. I didn't have a dorm room, so I slept on the floor in friends' rooms, I returned coke bottles for the 5 cent deposits to buy food with, and I would walk the 7 miles across town every Sunday night to get one good meal a week at the Hare Krishna"
    },
    {
      "who": "Steve Jobs",
      "start": 179,
      "text": "temple. I loved it."
    },
    {
      "who": "Steve Jobs",
      "start": 182,
      "text": "And much of what I stumbled into by following my curiosity and intuition turned out to be priceless later on."
    },
    {
      "who": "Steve Jobs",
      "start": 188,
      "text": "Let me give you one example: Reed College at that time offered perhaps the best calligraphy instruction in the country."
    },
    {
      "who": "Steve Jobs",
      "start": 196,
      "text": "Throughout the campus every poster, every label on every drawer, was beautifully hand calligraphed."
    },
    {
      "who": "Steve Jobs",
      "start": 203,
      "text": "Because I had dropped out and didn't have to take the normal classes, I decided to take a calligraphy class to learn how to do this."
    },
    {
      "who": "Steve Jobs",
      "start": 211,
      "text": "I learned about serif and san serif typefaces, about varying the amount of space between different letter combinations, about what makes great typography great."
    },
    {
      "who": "Steve Jobs",
      "start": 221,
      "text": "It was beautiful, historical, artistically subtle in a way that science can't capture, and I found it fascinating."
    },
    {
      "who": "Steve Jobs",
      "start": 230,
      "text": "None of this had even a hope of any practical application in my life."
    },
    {
      "who": "Steve Jobs",
      "start": 236,
      "text": "But ten years later, when we were designing the first Macintosh computer, it all came back to me. And we designed it all into the Mac."
    },
    {
      "who": "Steve Jobs",
      "start": 243,
      "text": "It was the first computer with beautiful typography."
    },
    {
      "who": "Steve Jobs",
      "start": 247,
      "text": "If I had never dropped in on that single course in college, the Mac would have never had multiple typefaces or proportionally spaced fonts."
    },
    {
      "who": "Steve Jobs",
      "start": 255,
      "text": "And since Windows just copied the Mac, it's likely that no personal computer would have them."
    },
    {
      "who": "Steve Jobs",
      "start": 265,
      "text": "If I had never dropped out, I would have never dropped in on this calligraphy class, and personal computers might not have the wonderful typography that they do. Of course it was impossible to connect the dots looking forward when I was in college."
    },
    {
      "who": "Steve Jobs",
      "start": 280,
      "text": "But it was very, very clear looking backwards ten years later."
    },
    {
      "who": "Steve Jobs",
      "start": 285,
      "text": "Again, you can't connect the dots looking forward;"
    },
    {
      "who": "Steve Jobs",
      "start": 288,
      "text": "you can only connect them looking backwards."
    },
    {
      "who": "Steve Jobs",
      "start": 291,
      "text": "So you have to trust that the dots will somehow connect in your future."
    },
    {
      "who": "Steve Jobs",
      "start": 295,
      "text": "You have to trust in something, your gut, destiny, life, karma, whatever."
    },
    {
      "who": "Steve Jobs",
      "start": 300,
      "text": "Beleiveing that the dots will connect down the road will give you the confidence to follow your heart Even when it leads you off the well worn path, and that will make all the difference."
    },
    {
      "who": "Steve Jobs",
      "start": 317,
      "text": "My second story is about love and loss."
    },
    {
      "who": "Steve Jobs",
      "start": 322,
      "text": "I was lucky I found what I loved to do early in life."
    },
    {
      "who": "Steve Jobs",
      "start": 326,
      "text": "Woz and I started Apple in my parents garage when I was 20."
    },
    {
      "who": "Steve Jobs",
      "start": 330,
      "text": "We worked hard, and in 10 years Apple had grown from just the two of us in a garage into a $2 billion company with over 4000 employees."
    },
    {
      "who": "Steve Jobs",
      "start": 338,
      "text": "We had just released our finest creation the Macintosh a year earlier, and I had just turned 30."
    },
    {
      "who": "Steve Jobs",
      "start": 344,
      "text": "And then I got fired."
    },
    {
      "who": "Steve Jobs",
      "start": 347,
      "text": "How can you get fired from a company you started?"
    },
    {
      "who": "Steve Jobs",
      "start": 350,
      "text": "Well, as Apple grew we hired someone who I thought was very talented to run the company with me, and for the first year or so things went well."
    },
    {
      "who": "Steve Jobs",
      "start": 358,
      "text": "But then our visions of the future began to diverge and eventually we had a falling out."
    },
    {
      "who": "Steve Jobs",
      "start": 364,
      "text": "When we did, our Board of Directors sided with him."
    },
    {
      "who": "Steve Jobs",
      "start": 367,
      "text": "So at 30 I was out. And very publicly out."
    },
    {
      "who": "Steve Jobs",
      "start": 371,
      "text": "What had been the focus of my entire adult life was gone, and it was devastating."
    },
    {
      "who": "Steve Jobs",
      "start": 377,
      "text": "I really didn't know what to do for a few months."
    },
    {
      "who": "Steve Jobs",
      "start": 379,
      "text": "I felt that I had let the previous generation of entrepreneurs down - that I had dropped the baton as it was being passed to me."
    },
    {
      "who": "Steve Jobs",
      "start": 385,
      "text": "I met with David Packard and Bob Noyce and tried to apologize for screwing up so badly."
    },
    {
      "who": "Steve Jobs",
      "start": 392,
      "text": "I was a very public failure, and I even thought about running away from the valley."
    },
    {
      "who": "Steve Jobs",
      "start": 397,
      "text": "But something slowly began to dawn on me I still loved what I did."
    },
    {
      "who": "Steve Jobs",
      "start": 402,
      "text": "The turn of events at Apple had not changed that one bit."
    },
    {
      "who": "Steve Jobs",
      "start": 406,
      "text": "I had been rejected, but I was still in love."
    },
    {
      "who": "Steve Jobs",
      "start": 410,
      "text": "And so I decided to start over."
    },
    {
      "who": "Steve Jobs",
      "start": 413,
      "text": "I didn't see it then, but it turned out that getting fired from Apple was the best thing that could have ever happened to me."
    },
    {
      "who": "Steve Jobs",
      "start": 419,
      "text": "The heaviness of being successful was replaced by the lightness of being a beginner again, less sure about everything."
    },
    {
      "who": "Steve Jobs",
      "start": 425,
      "text": "It freed me to enter one of the most creative periods of my life."
    },
    {
      "who": "Steve Jobs",
      "start": 429,
      "text": "During the next five years, I started a company named NeXT, another company named Pixar, and fell in love with an amazing woman who would become my wife."
    },
    {
      "who": "Steve Jobs",
      "start": 438,
      "text": "Pixar went on to create the worlds first computer animated feature film, Toy Story, and is now the most successful animation studio in the world."
    },
    {
      "who": "Steve Jobs",
      "start": 448,
      "text": "In a remarkable turn of events, Apple bought NeXT, I returned to Apple, and the technology we developed at NeXT is at the heart of Apple's current renaissance."
    },
    {
      "who": "Steve Jobs",
      "start": 458,
      "text": "And Laurene and I have a wonderful family together."
    },
    {
      "who": "Steve Jobs",
      "start": 462,
      "text": "I'm pretty sure none of this would have happened if I hadn't been fired from Apple."
    },
    {
      "who": "Steve Jobs",
      "start": 466,
      "text": "It was awful tasting medicine, but I guess the patient needed it."
    },
    {
      "who": "Steve Jobs",
      "start": 470,
      "text": "Sometimes life hits you in the head with a brick. Don't lose faith."
    },
    {
      "who": "Steve Jobs",
      "start": 476,
      "text": "I'm convinced that the only thing that kept me going was that I loved what I did. You've got to find what you love."
    },
    {
      "who": "Steve Jobs",
      "start": 483,
      "text": "And that is as true for your work as it is for your lovers."
    },
    {
      "who": "Steve Jobs",
      "start": 486,
      "text": "Your work is going to fill a large part of your life, and the only way to be truly satisfied is to do what you believe is great work."
    },
    {
      "who": "Steve Jobs",
      "start": 493,
      "text": "And the only way to do great work is to love what you do."
    },
    {
      "who": "Steve Jobs",
      "start": 496,
      "text": "If you haven't found it yet, keep looking. Don't settle."
    },
    {
      "who": "Steve Jobs",
      "start": 502,
      "text": "As with all matters of the heart, you'll know when you find it."
    },
    {
      "who": "Steve Jobs",
      "start": 506,
      "text": "And, like any great relationship, it just gets better and better as the years roll on."
    },
    {
      "who": "Steve Jobs",
      "start": 510,
      "text": "So keep looking. Don't settle."
    },
    {
      "who": "Steve Jobs",
      "start": 523,
      "text": "My third story is about death."
    },
    {
      "who": "Steve Jobs",
      "start": 527,
      "text": "When I was 17, I read a quote that went something like: \"If you live each day as if it was your last, someday you'll most certainly be right.\""
    },
    {
      "who": "Steve Jobs",
      "start": 539,
      "text": "It made an impression on me, and since then, for the past 33 years, I have looked in the mirror every morning and asked myself: \"If today were the last day of my life, would I want to do what I am about to do today?\""
    },
    {
      "who": "Steve Jobs",
      "start": 552,
      "text": "And whenever the answer has been \"No\" for too many days in a row, I know I need to change something."
    },
    {
      "who": "Steve Jobs",
      "start": 559,
      "text": "Remembering that I'll be dead soon is the most important tool I've ever encountered to help me make the big choices in life."
    },
    {
      "who": "Steve Jobs",
      "start": 566,
      "text": "Because almost everything all external expectations, all pride, all fear of embarrassment or failure - these things just fall away in the face of death, leaving only what is truly important."
    },
    {
      "who": "Steve Jobs",
      "start": 579,
      "text": "Remembering that you are going to die is the best way I know to avoid the trap of thinking you have something to lose."
    },
    {
      "who": "Steve Jobs",
      "start": 586,
      "text": "You are already naked. There is no reason not to follow your heart."
    },
    {
      "who": "Steve Jobs",
      "start": 592,
      "text": "About a year ago I was diagnosed with cancer."
    },
    {
      "who": "Steve Jobs",
      "start": 595,
      "text": "I had a scan at 7:30 in the morning, and it clearly showed a tumor on my pancreas."
    },
    {
      "who": "Steve Jobs",
      "start": 602,
      "text": "I didn't even know what a pancreas was."
    },
    {
      "who": "Steve Jobs",
      "start": 604,
      "text": "The doctors told me this was almost certainly a type of cancer that is incurable, and that I should expect to live no longer than three to six months."
    },
    {
      "who": "Steve Jobs",
      "start": 614,
      "text": "My doctor advised me to go home and get my affairs in order, which is doctor's code for prepare to die."
    },
    {
      "who": "Steve Jobs",
      "start": 621,
      "text": "It means to try to tell your kids everything you thought you'd have the next 10 years to tell them in just a few months."
    },
    {
      "who": "Steve Jobs",
      "start": 630,
      "text": "It means to make sure everything is buttoned up so that it will be as easy as possible for your family."
    },
    {
      "who": "Steve Jobs",
      "start": 635,
      "text": "It means to say your goodbyes."
    },
    {
      "who": "Steve Jobs",
      "start": 639,
      "text": "I lived with that diagnosis all day."
    },
    {
      "who": "Steve Jobs",
      "start": 642,
      "text": "Later that evening I had a biopsy, where they stuck an endoscope down my throat, through my stomach and into my intestines, put a needle into my pancreas and got a few cells from the tumor."
    },
    {
      "who": "Steve Jobs",
      "start": 652,
      "text": "I was sedated, but my wife, who was there, told me that when they viewed the cells under a microscope the doctors started crying because it turned out to be a very rare form of pancreatic cancer that is curable with surgery."
    },
    {
      "who": "Steve Jobs",
      "start": 667,
      "text": "I had the surgery and thankfully I'm fine now."
    },
    {
      "who": "Steve Jobs",
      "start": 679,
      "text": "This was the closest I've been to facing death, and I hope its the closest I get for a few more decades."
    },
    {
      "who": "Steve Jobs",
      "start": 685,
      "text": "Having lived through it, I can now say this to you with a bit more certainty than when death was a useful but purely intellectual concept: No one wants to die."
    },
    {
      "who": "Steve Jobs",
      "start": 696,
      "text": "Even people who want to go to heaven don't want to die to get there."
    },
    {
      "who": "Steve Jobs",
      "start": 700,
      "text": "And yet death is the destination we all share."
    },
    {
      "who": "Steve Jobs",
      "start": 704,
      "text": "No one has ever escaped it. And that is as it should be, because Death is very likely the single best invention of Life."
    },
    {
      "who": "Steve Jobs",
      "start": 713,
      "text": "It is Life's change agent."
    },
    {
      "who": "Steve Jobs",
      "start": 715,
      "text": "It clears out the old to make way for the new."
    },
    {
      "who": "Steve Jobs",
      "start": 718,
      "text": "Right now the new is you, but someday not too long from now, you will gradually become the old and be cleared away."
    },
    {
      "who": "Steve Jobs",
      "start": 727,
      "text": "Sorry to be so dramatic, but it is quite true."
    },
    {
      "who": "Steve Jobs",
      "start": 730,
      "text": "Your time is limited, so don't waste it living someone else's life."
    },
    {
      "who": "Steve Jobs",
      "start": 736,
      "text": "Don't be trapped by dogma which is living with the results of other people's thinking."
    },
    {
      "who": "Steve Jobs",
      "start": 741,
      "text": "Don't let the noise of others' opinions drown out your own inner voice. And most important, have the courage to follow your heart and intuition."
    },
    {
      "who": "Steve Jobs",
      "start": 750,
      "text": "They somehow already know what you truly want to become."
    },
    {
      "who": "Steve Jobs",
      "start": 754,
      "text": "Everything else is secondary."
    },
    {
      "who": "Steve Jobs",
      "start": 768,
      "text": "When I was young, there was an amazing publication called The Whole Earth Catalog, which was one of the bibles of my generation."
    },
    {
      "who": "Steve Jobs",
      "start": 776,
      "text": "It was created by a fellow named Stewart Brand not far from here in Menlo Park, and he brought it to life with his poetic touch."
    },
    {
      "who": "Steve Jobs",
      "start": 784,
      "text": "This was in the late 1960's, before personal computers and desktop publishing, so it was all made with typewriters, scissors, and polaroid cameras."
    },
    {
      "who": "Steve Jobs",
      "start": 793,
      "text": "It was sort of like Google in paperback form, 35 years before Google came along: it was idealistic, overflowing with neat tools, and great notions."
    },
    {
      "who": "Steve Jobs",
      "start": 803,
      "text": "Stewart and his team put out several issues of The Whole Earth Catalog, and then when it had run its course, they put out a final issue."
    },
    {
      "who": "Steve Jobs",
      "start": 811,
      "text": "It was the mid-1970s, and I was your age."
    },
    {
      "who": "Steve Jobs",
      "start": 817,
      "text": "On the back cover of their final issue was a photograph of an early morning country road, the kind you might find yourself hitchhiking on if you were so adventurous."
    },
    {
      "who": "Steve Jobs",
      "start": 827,
      "text": "Beneath it were the words: \"Stay Hungry. Stay Foolish.\""
    },
    {
      "who": "Steve Jobs",
      "start": 831,
      "text": "It was their farewell message as they signed off. Stay Hungry."
    },
    {
      "who": "Steve Jobs",
      "start": 837,
      "text": "Stay Foolish. And I have always wished that for myself."
    },
    {
      "who": "Steve Jobs",
      "start": 842,
      "text": "And now, as you graduate to begin anew, I wish that for you."
    },
    {
      "who": "Steve Jobs",
      "start": 847,
      "text": "Stay Hungry. Stay Foolish."
    },
    {
      "who": "Steve Jobs",
      "start": 850,
      "text": "Thank you all very much."
    },
    {
      "who": "Speaker A",
      "start": 876,
      "text": "The preceding program is copyrighted by Stanford University."
    },
    {
      "who": "Speaker A",
      "start": 879,
      "text": "Please visit us at stanford.edu"
    }
  ],
  "chapters": [
    {
      "start": 0,
      "end": 152,
      "title": "退学与人生起点",
      "description": "乔布斯分享自己未毕业的经历，讲述了被收养的背景以及因学费昂贵和迷茫而选择从大学退学的决定。"
    },
    {
      "start": 152,
      "end": 317,
      "title": "兴趣与点滴相连",
      "description": "退学后，乔布斯旁听了书法课，这些看似无用的知识在十年后启发了Macintosh的字体设计，他强调要相信点滴终将连接。"
    },
    {
      "start": 317,
      "end": 476,
      "title": "苹果被解雇与重生",
      "description": "乔布斯讲述了被自己创立的苹果公司解雇的经历，这虽然痛苦，却让他得以重新开始，创立NeXT和Pixar，最终重返苹果。"
    },
    {
      "start": 476,
      "end": 523,
      "title": "追寻所爱，永不妥协",
      "description": "乔布斯强调，只有热爱自己的工作才能获得真正的满足，并鼓励毕业生们不断寻找所爱，永不妥协。"
    },
    {
      "start": 523,
      "end": 685,
      "title": "死亡的生命视角",
      "description": "乔布斯分享了死亡意识如何帮助他做出重要人生选择，并讲述了自己被诊断出胰腺癌后又奇迹般治愈的经历。"
    },
    {
      "start": 685,
      "end": 768,
      "title": "死亡与活出自我",
      "description": "他认为死亡是生命最伟大的发明，鼓励人们不要浪费时间活在别人的期望中，要勇敢追随自己的内心和直觉。"
    },
    {
      "start": 768,
      "end": 909,
      "title": "保持饥饿，保持愚蠢",
      "description": "乔布斯引用《全球目录》的告别语“求知若饥，虚心若愚”，以此作为对毕业生的期许和祝福。"
    }
  ],
  "t_segments": [
    {
      "id": "T1",
      "start_sec": 0,
      "end_sec": 317,
      "topic": "人生点滴相连：相信直觉，回头看才能串联线索",
      "summary": "乔布斯讲述自己的出生和大学辍学经历，以及旁听书法课如何影响Macintosh的字体设计。他强调人生中的点滴只有在回顾时才能串联起来，因此要相信直觉，追随内心。"
    },
    {
      "id": "T2",
      "start_sec": 317,
      "end_sec": 523,
      "topic": "爱与失去：被苹果解雇后的重生与发现真爱",
      "summary": "乔布斯回忆被自己创立的苹果公司解雇的痛苦，以及这段经历如何促使他创立NeXT和Pixar，并最终重回苹果。他强调热爱自己所做之事是坚持下去的唯一动力，并鼓励人们不断寻找自己的热爱。"
    },
    {
      "id": "T3",
      "start_sec": 523,
      "end_sec": 909,
      "topic": "死亡的意义：活出真实自我，保持求知若饥虚心若愚",
      "summary": "乔布斯分享他对死亡的思考，以及被诊断出癌症后的经历，这让他更深刻地理解生命的有限。他鼓励毕业生不要浪费时间活在别人的影子里，要勇于追随内心和直觉，并以《全球概览》的告别语“求知若饥，虚心若愚”作为对毕业生的寄语。"
    }
  ],
  "p_segments": [
    {
      "id": "T1_P1",
      "parent_t_id": "T1",
      "start_sec": 182,
      "end_sec": 317,
      "duration_sec": 135,
      "question": "如何相信直觉，让看似无用的经历在未来发挥价值？",
      "insight": "你无法预见未来，只能在回顾时串联起人生中的点滴。所以，要相信你的直觉和内心，即使它让你偏离常轨，最终也会带来巨大的不同。",
      "domain": [
        "学习与思维方法",
        "个人成长与状态"
      ],
      "fine_tags": [
        "连接点滴",
        "相信直觉",
        "回头看",
        "非线性路径"
      ],
      "transcript": "And much of what I stumbled into by following my curiosity and intuition turned out to be priceless later on. Let me give you one example: Reed College at that time offered perhaps the best calligraphy instruction in the country. Throughout the campus every poster, every label on every drawer, was beautifully hand calligraphed. Because I had dropped out and didn't have to take the normal classes, I decided to take a calligraphy class to learn how to do this. I learned about serif and san serif typefaces, about varying the amount of space between different letter combinations, about what makes great typography great. It was beautiful, historical, artistically subtle in a way that science can't capture, and I found it fascinating. None of this had even a hope of any practical application in my life. But ten years later, when we were designing the first Macintosh computer, it all came back to me. And we designed it all into the Mac. It was the first computer with beautiful typography. If I had never dropped in on that single course in college, the Mac would have never had multiple typefaces or proportionally spaced fonts. And since Windows just copied the Mac, it's likely that no personal computer would have them. If I had never dropped out, I would have never dropped in on this calligraphy class, and personal computers might not have the wonderful typography that they do. Of course it was impossible to connect the dots looking forward when I was in college. But it was very, very clear looking backwards ten years later. Again, you can't connect the dots looking forward; you can only connect them looking backwards. So you have to trust that the dots will somehow connect in your future. You have to trust in something, your gut, destiny, life, karma, whatever. Beleiveing that the dots will connect down the road will give you the confidence to follow your heart Even when it leads you off the well worn path, and that will make all the difference."
    },
    {
      "id": "T2_P1",
      "parent_t_id": "T2",
      "start_sec": 413,
      "end_sec": 470,
      "duration_sec": 57,
      "question": "被公司开除后，如何才能凤凰涅槃？",
      "insight": "被公司解雇虽然痛苦，但它卸下了成功的重负，让我重回初心，反而激发了人生中最具创造力的时期，并最终带来了更大的成功和个人幸福。",
      "domain": [
        "个人成长与状态",
        "创业与起步"
      ],
      "fine_tags": [
        "被解雇",
        "凤凰涅槃",
        "放下成功",
        "重新开始",
        "创造力爆发"
      ],
      "transcript": "I didn't see it then, but it turned out that getting fired from Apple was the best thing that could have ever happened to me. The heaviness of being successful was replaced by the lightness of being a beginner again, less sure about everything. It freed me to enter one of the most creative periods of my life. During the next five years, I started a company named NeXT, another company named Pixar, and fell in love with an amazing woman who would become my wife. Pixar went on to create the worlds first computer animated feature film, Toy Story, and is now the most successful animation studio in the world. In a remarkable turn of events, Apple bought NeXT, I returned to Apple, and the technology we developed at NeXT is at the heart of Apple's current renaissance. And Laurene and I have a wonderful family together. I'm pretty sure none of this would have happened if I hadn't been fired from Apple. It was awful tasting medicine, but I guess the patient needed it."
    },
    {
      "id": "T3_P1",
      "parent_t_id": "T3",
      "start_sec": 539,
      "end_sec": 592,
      "duration_sec": 53,
      "question": "如何利用死亡意识，做出重要人生选择？",
      "insight": "每天自问“如果今天是最后一天，我还会做现在的事吗？”能帮助你剥离外部期望和恐惧，看清真正重要的事，从而勇敢追随内心。",
      "domain": [
        "个人成长与状态",
        "决策与判断"
      ],
      "fine_tags": [
        "死亡意识",
        "人生选择",
        "追随内心",
        "摆脱恐惧",
        "活出自我"
      ],
      "transcript": "It made an impression on me, and since then, for the past 33 years, I have looked in the mirror every morning and asked myself: \"If today were the last day of my life, would I want to do what I am about to do today?\" And whenever the answer has been \"No\" for too many days in a row, I know I need to change something. Remembering that I'll be dead soon is the most important tool I've ever encountered to help me make the big choices in life. Because almost everything all external expectations, all pride, all fear of embarrassment or failure - these things just fall away in the face of death, leaving only what is truly important. Remembering that you are going to die is the best way I know to avoid the trap of thinking you have something to lose. You are already naked. There is no reason not to follow your heart."
    },
    {
      "id": "T3_P2",
      "parent_t_id": "T3",
      "start_sec": 685,
      "end_sec": 730,
      "duration_sec": 45,
      "question": "死亡对生命来说是好事吗？",
      "insight": "死亡是生命最伟大的发明，它是变革的推动者，清除旧事物，为新事物腾出空间，确保生命不断更新和演进。",
      "domain": [
        "学习与思维方法",
        "个人成长与状态"
      ],
      "fine_tags": [
        "死亡哲学",
        "生命变革",
        "新陈代谢",
        "演化机制"
      ],
      "transcript": "Having lived through it, I can now say this to you with a bit more certainty than when death was a useful but purely intellectual concept: No one wants to die. Even people who want to go to heaven don't want to die to get there. And yet death is the destination we all share. No one has ever escaped it. And that is as it should be, because Death is very likely the single best invention of Life. It is Life's change agent. It clears out the old to make way for the new. Right now the new is you, but someday not too long from now, you will gradually become the old and be cleared away. Sorry to be so dramatic, but it is quite true."
    }
  ]
}
